README.md
setup.py
xmat/__init__.py
xmat/__main__.py
xmat/benchmark.py
xmat/datastream.py
xmat/tcpsocket.py
xmat.egg-info/PKG-INFO
xmat.egg-info/SOURCES.txt
xmat.egg-info/dependency_links.txt
xmat.egg-info/entry_points.txt
xmat.egg-info/requires.txt
xmat.egg-info/top_level.txt