Metadata-Version: 2.1
Name: xmat
Version: 1.0.0
Summary: library for nympy.ndarray serialization to file or network
Home-page: https://github.com/signalarray/xmat
Author: Vadim Kozub
Author-email: signal.array@gmail.com
License: MIT
Project-URL: Documentation, https://https://xmat.readthedocs.io
Keywords: serialization multi-dimensional-array binary-format socket tcp c++ cpp matlab
Platform: UNKNOWN
Classifier: License :: OSI Approved :: MIT License
Classifier: Programming Language :: Python :: 3.10
Classifier: Operating System :: OS Independent
Classifier: Topic :: File Formats
Requires-Python: >=3.10
